custom_field/__init__.py
custom_field/admin.py
custom_field/custom_field.py
custom_field/models.py
custom_field/tests.py
custom_field/migrations/0001_initial.py
custom_field/migrations/0002_auto_20150119_2032.py
custom_field/migrations/0003_customfield_mask.py
custom_field/migrations/0004_django2_upgrade.py
custom_field/migrations/__init__.py
custom_field/templates/admin/includes/custom_field_fieldset.html
django_custom_field-3.0.dist-info/DESCRIPTION.rst
django_custom_field-3.0.dist-info/METADATA
django_custom_field-3.0.dist-info/RECORD
django_custom_field-3.0.dist-info/WHEEL
django_custom_field-3.0.dist-info/metadata.json
django_custom_field-3.0.dist-info/top_level.txt
