Metadata-Version: 2.0
Name: django-custom-field
Version: 3.0
Summary: End user custom fields for Django including contrib.admin support
Home-page: http://github.com/willseward/django-custom-field
Author: David Burke
Author-email: wward@warddevelopment.com
License: MIT
Keywords: django admin
Platform: UNKNOWN
Classifier: Development Status :: 5 - Production/Stable
Classifier: Environment :: Web Environment
Classifier: Framework :: Django
Classifier: Programming Language :: Python
Classifier: Programming Language :: Python :: 2.7
Classifier: Programming Language :: Python :: 3.4
Classifier: Programming Language :: Python :: 3.5
Classifier: Programming Language :: Python :: 3.6
Classifier: Programming Language :: Python :: 3.7
Classifier: Programming Language :: Python :: 3.8
Classifier: Intended Audience :: Developers
Classifier: Intended Audience :: System Administrators
Classifier: License :: OSI Approved :: MIT License
Requires-Dist: django
